langgraph_checkpoint_cloudflare_d1/__init__.py
langgraph_checkpoint_cloudflare_d1/aio.py
langgraph_checkpoint_cloudflare_d1/models.py
langgraph_checkpoint_cloudflare_d1/py.typed
langgraph_checkpoint_cloudflare_d1/utils.py
langgraph_checkpoint_cloudflare_d1-0.1.5.dist-info/METADATA
langgraph_checkpoint_cloudflare_d1-0.1.5.dist-info/WHEEL
langgraph_checkpoint_cloudflare_d1-0.1.5.dist-info/RECORD
