Metadata-Version: 2.4
Name: langgraph-checkpoint-cloudflare-d1
Version: 0.1.5
Summary: LangGraph Checkpoint implementation for Cloudflare D1
Project-URL: Source Code, https://github.com/cloudflare/langchain-cloudflare/libs/langgraph-checkpoint-cloudflare-d1
Project-URL: Release Notes, https://github.com/cloudflare/langchain-cloudflare/libs/langgraph-checkpoint-cloudflare-d1/blob/main/README.md
License-Expression: MIT
Requires-Python: >=3.10
Requires-Dist: httpx>=0.24.1
Requires-Dist: langchain-core>=0.3.81
Requires-Dist: langgraph-checkpoint>=3.0.0
Requires-Dist: langgraph>=1.0.0
Requires-Dist: packaging>=20.0
Requires-Dist: pydantic<3.0.0,>=1.10.0
Requires-Dist: requests>=2.31.0
Requires-Dist: tenacity>=8.0.0
